pipeline_cli/__about__.py
pipeline_cli/__init__.py
pipeline_cli-1.0.15.dist-info/DESCRIPTION.rst
pipeline_cli-1.0.15.dist-info/METADATA
pipeline_cli-1.0.15.dist-info/RECORD
pipeline_cli-1.0.15.dist-info/WHEEL
pipeline_cli-1.0.15.dist-info/entry_points.txt
pipeline_cli-1.0.15.dist-info/metadata.json
pipeline_cli-1.0.15.dist-info/top_level.txt
