Metadata-Version: 2.0
Name: pipeline-cli
Version: 1.0.15
Summary: Command-line interface to Sepior pipeline server.
Home-page: https://github.com/Sepior/pipeline-cli
Author: Janus Friis Nielsen
Author-email: jfn@sepior.com
License: Proprietary
Keywords: Sepior pipeline
Platform: UNKNOWN
Classifier: Development Status :: 5 - Production/Stable
Classifier: Intended Audience :: Developers
Classifier: Topic :: Software Development :: Build Tools
Classifier: License :: Other/Proprietary License
Classifier: Programming Language :: Python :: 3.5
Requires-Dist: requests
